paragrid/__init__.py
paragrid/paradec.py
paragrid/paragrid.py
paragrid/version.py
paragrid-0.0.10.dist-info/LICENSE
paragrid-0.0.10.dist-info/METADATA
paragrid-0.0.10.dist-info/WHEEL
paragrid-0.0.10.dist-info/top_level.txt
paragrid-0.0.10.dist-info/RECORD
