Metadata-Version: 2.1
Name: paragrid
Version: 0.0.10
Summary: Simple parallelized grid search to find the best hyperparameters
Home-page: https://github.com/malteal/paragrid
Author: Malte Algren
Author-email: malte__algren@hotmail.com
License: MIT
Download-URL: https://github.com/malteal/paragrid/archive/0.0.9.tar.gz
Keywords: machinelearning,gridsearchcv,parallel-computing
Platform: UNKNOWN
Classifier: Development Status :: 3 - Alpha
Classifier: Intended Audience :: Developers
Classifier: Topic :: Software Development :: Build Tools
Classifier: License :: OSI Approved :: MIT License
Classifier: Programming Language :: Python :: 3
Classifier: Programming Language :: Python :: 3.4
Classifier: Programming Language :: Python :: 3.5
Classifier: Programming Language :: Python :: 3.6
Classifier: Programming Language :: Python :: 3.7
Requires-Dist: numpy
Requires-Dist: sklearn
Requires-Dist: matplotlib
Requires-Dist: xgboost
Requires-Dist: lightgbm
